crane_fmu/__init__.py
crane_fmu/boom.py
crane_fmu/crane.py
crane_fmu/logger.py
crane_fmu/py.typed
crane_fmu-0.1.1.dist-info/METADATA
crane_fmu-0.1.1.dist-info/WHEEL
crane_fmu-0.1.1.dist-info/entry_points.txt
crane_fmu-0.1.1.dist-info/licenses/LICENSE
crane_fmu-0.1.1.dist-info/RECORD
