Metadata-Version: 2.4
Name: Crane-FMU
Version: 0.1.1
Summary: Basic crane simulation model including publication as FMU, for usage in the SEACo project
Project-URL: Homepage, https://github.com/dnv-opensource/crane-fmu
Project-URL: Documentation, https://dnv-innersource.github.io/crane-fmu/README.html
Project-URL: Repository, https://github.com/dnv-opensource/crane-fmu.git
Project-URL: Issues, https://github.com/dnv-opensource/crane-fmu/issues
Project-URL: Changelog, https://github.com/dnv-opensource/crane-fmu/blob/main/CHANGELOG.md
Author-email: Siegfried Eisinger <Siegfried.Eisinger@DNV.com>
License: MIT License
License-File: LICENSE
Keywords: FMI,OSP,crane,model,simulation,tight coupling
Classifier: Development Status :: 3 - Alpha
Classifier: Environment :: Console
Classifier: Intended Audience :: Developers
Classifier: Intended Audience :: Science/Research
Classifier: License :: OSI Approved :: MIT License
Classifier: Operating System :: Microsoft :: Windows
Classifier: Operating System :: POSIX :: Linux
Classifier: Programming Language :: Python :: 3.10
Classifier: Programming Language :: Python :: 3.11
Classifier: Programming Language :: Python :: 3.12
Classifier: Topic :: Scientific/Engineering
Classifier: Topic :: Software Development :: Libraries :: Python Modules
Requires-Python: >=3.10
Requires-Dist: component-model>=0.1.0
Requires-Dist: fmpy>=0.3.22
Requires-Dist: matplotlib>=3.10
Requires-Dist: numpy<2.0,>=1.26
Requires-Dist: pythonfmu>=0.6.5
Provides-Extra: editor
Requires-Dist: thonny>=4.0.2; extra == 'editor'
Provides-Extra: rest
Requires-Dist: docutils>=0.3; extra == 'rest'
